mantel/__init__.py
mantel/_plot.py
mantel/_test.py
mantel/_version.py
mantel-2.2.1.dist-info/LICENSE.md
mantel-2.2.1.dist-info/METADATA
mantel-2.2.1.dist-info/WHEEL
mantel-2.2.1.dist-info/top_level.txt
mantel-2.2.1.dist-info/RECORD
