Metadata-Version: 2.1
Name: mantel
Version: 2.2.1
Summary: Python implementation of the Mantel test, a significance test of the correlation between two distance matrices
Home-page: https://github.com/jwcarr/mantel
Author: Jon Carr
Author-email: jcarr@sissa.it
License: MIT
Classifier: Programming Language :: Python :: 3
Classifier: License :: OSI Approved :: MIT License
Classifier: Operating System :: OS Independent
Classifier: Development Status :: 5 - Production/Stable
Classifier: Intended Audience :: Science/Research
Classifier: Topic :: Scientific/Engineering :: Mathematics
Requires-Python: >=3.6
License-File: LICENSE.md
Requires-Dist: numpy >=1.10
Requires-Dist: scipy >=1.0
